<?xml version="1.0" encoding="UTF-8"?>

<SearchParameter xmlns="http://hl7.org/fhir">
  <id value="ror-sp-healthcareservice-intervention-zone"/>
  <text>
    <status value="generated"/><div xmlns="http://www.w3.org/1999/xhtml"><h2>RORHealthcareServiceInterventionZone</h2><p>Parameter <code>intervention-zone</code>:<code>token</code></p><div><p>Paramètre de recherche décrivant la zone d'intervention</p>
</div><table class="grid"><tr><td>Resource</td><td><a href="http://hl7.org/fhir/R4/healthcareservice.html">HealthcareService</a></td></tr><tr><td>Expression</td><td><code>HealthcareService.extension.where(url='http://interop.esante.gouv.fr/fhir/ig/ror30/StructureDefinition/ror-healthcareservice-intervention-zone').extension(url='interventionZone').valueCodeableConcept</code></td></tr><tr><td>Multiples</td><td>The parameter cannot repeat or have multiple values</td></tr></table></div>
  </text>
  <url value="http://interop.esante.gouv.fr/fhir/ig/ror30/SearchParameter/ror-sp-healthcareservice-intervention-zone"/>
  <version value="3.0"/>
  <name value="RORHealthcareServiceInterventionZone"/>
  <status value="active"/>
  <date value="2023-02-17T16:29:47+00:00"/>
  <publisher value="ANS"/>
  <contact>
    <name value="ANS"/>
    <telecom>
      <system value="url"/>
      <value value="https://esante.gouv.fr"/>
    </telecom>
  </contact>
  <description value="Paramètre de recherche décrivant la zone d'intervention"/>
  <code value="intervention-zone"/>
  <base value="HealthcareService"/>
  <type value="token"/>
  <expression value="HealthcareService.extension.where(url='http://interop.esante.gouv.fr/fhir/ig/ror30/StructureDefinition/ror-healthcareservice-intervention-zone').extension(url='interventionZone').valueCodeableConcept"/>
</SearchParameter>